src/Common.py
src/Contract.py
src/Ensure.py
src/Invariant.py
src/Preserve.py
src/Require.py
src/Types.py
src/__init__.py
fracture_contracts-0.1.dist-info/METADATA
fracture_contracts-0.1.dist-info/WHEEL
fracture_contracts-0.1.dist-info/top_level.txt
fracture_contracts-0.1.dist-info/RECORD
